pabutools/__init__.py
pabutools/fractions.py
pabutools/tiebreaking.py
pabutools/utils.py
pabutools/analysis/__init__.py
pabutools/analysis/category.py
pabutools/analysis/cohesiveness.py
pabutools/analysis/fairshare.py
pabutools/analysis/instanceproperties.py
pabutools/analysis/justifiedrepresentation.py
pabutools/analysis/mesanalytics.py
pabutools/analysis/paretooptimality.py
pabutools/analysis/priceability.py
pabutools/analysis/priceability_python_mip.py
pabutools/analysis/priceability_relaxation.py
pabutools/analysis/priceability_relaxation_python_mip.py
pabutools/analysis/profileproperties.py
pabutools/analysis/votersatisfaction.py
pabutools/election/__init__.py
pabutools/election/instance.py
pabutools/election/pabulib.py
pabutools/election/preflib.py
pabutools/election/ballot/__init__.py
pabutools/election/ballot/approvalballot.py
pabutools/election/ballot/ballot.py
pabutools/election/ballot/cardinalballot.py
pabutools/election/ballot/cumulativeballot.py
pabutools/election/ballot/ordinalballot.py
pabutools/election/profile/__init__.py
pabutools/election/profile/approvalprofile.py
pabutools/election/profile/cardinalprofile.py
pabutools/election/profile/cumulativeprofile.py
pabutools/election/profile/ordinalprofile.py
pabutools/election/profile/profile.py
pabutools/election/satisfaction/__init__.py
pabutools/election/satisfaction/additivesatisfaction.py
pabutools/election/satisfaction/functionalsatisfaction.py
pabutools/election/satisfaction/positionalsatisfaction.py
pabutools/election/satisfaction/satisfactionmeasure.py
pabutools/election/satisfaction/satisfactionprofile.py
pabutools/rules/__init__.py
pabutools/rules/budgetallocation.py
pabutools/rules/composition.py
pabutools/rules/cstv.py
pabutools/rules/exhaustion.py
pabutools/rules/maximin_support.py
pabutools/rules/maxwelfare.py
pabutools/rules/pb_ear.py
pabutools/rules/phragmen.py
pabutools/rules/greedywelfare/__init__.py
pabutools/rules/greedywelfare/greedywelfare_details.py
pabutools-1.2.3.dist-info/licenses/LICENSE.md
pabutools-1.2.3.dist-info/WHEEL
pabutools-1.2.3.dist-info/METADATA
pabutools-1.2.3.dist-info/RECORD
