Metadata-Version: 2.4
Name: pabutools
Version: 1.2.3
Summary: Implementation of all the tools necessary to explore and analyse participatory budgeting elections
Author-email: Simon Rey <simon.j.rey@proton.me>, Grzegorz Pierczyński <g.pierczynski@mimuw.edu.pl>, Markus Utke <markusutke@gmx.de>, Piotr Skowron <p.skowron@mimuw.edu.pl>
Requires-Python: >=3.9
Classifier: Programming Language :: Python :: 3
Classifier: License :: OSI Approved :: GNU General Public License v3 or later (GPLv3+)
Classifier: Operating System :: OS Independent
Classifier: Programming Language :: Python :: 3.9
Classifier: Programming Language :: Python :: 3.10
Classifier: Programming Language :: Python :: 3.11
Classifier: Programming Language :: Python :: 3.12
Classifier: Programming Language :: Python :: 3.13
License-File: LICENSE.md
Requires-Dist: numpy
Requires-Dist: gmpy2>=2.1.5
Requires-Dist: preflibtools>=2.0.33
Requires-Dist: natsort
Requires-Dist: pulp
Requires-Dist: gurobipy
Requires-Dist: coverage ; extra == "dev"
Requires-Dist: Sphinx ; extra == "dev"
Requires-Dist: sphinx-book-theme ; extra == "dev"
Requires-Dist: sphinxcontrib-napoleon ; extra == "dev"
Requires-Dist: unittest2 ; extra == "dev"
Requires-Dist: parameterized ; extra == "dev"
Requires-Dist: sphinx-toolbox ; extra == "dev"
Requires-Dist: enum-tools ; extra == "dev"
Requires-Dist: abcvoting ; extra == "dev"
Requires-Dist: pyyaml ; extra == "dev"
Project-URL: Bug Tracker, https://github.com/comsoc-community/pabutools/issues
Project-URL: Homepage, https://github.com/comsoc-community/pabutools
Provides-Extra: dev
